gpapi/__init__.py
gpapi/config.py
gpapi/device.properties
gpapi/googleplay.py
gpapi/googleplay_pb2.py
gpapi/utils.py
gpapi-0.4.4.dist-info/LICENSE.md
gpapi-0.4.4.dist-info/METADATA
gpapi-0.4.4.dist-info/WHEEL
gpapi-0.4.4.dist-info/top_level.txt
gpapi-0.4.4.dist-info/RECORD
