Metadata-Version: 1.0
Name: gpapi
Version: 0.4.4
Summary: Unofficial python api for google play
Home-page: https://github.com/NoMore201/googleplay-api
Author: NoMore201
Author-email: domenico.iezzi.201@gmail.com
License: GPL3
Platform: UNKNOWN
